rcurl.py
rcurl-0.0.2.dist-info/METADATA
rcurl-0.0.2.dist-info/WHEEL
rcurl-0.0.2.dist-info/top_level.txt
rcurl-0.0.2.dist-info/RECORD
