Metadata-Version: 2.1
Name: rcurl
Version: 0.0.2
Summary: Generate curl commands from python-requests
Home-page: https://github.com/rapando/rcurl
Author: Samson Rapando
Author-email: samsonrapando@gmail.com
License: UNKNOWN
Platform: UNKNOWN
Classifier: Programming Language :: Python :: 3
Classifier: Programming Language :: Python :: 3.6
Classifier: Programming Language :: Python :: 3.7
Classifier: License :: OSI Approved :: GNU General Public License v2 or later (GPLv2+)
Classifier: Operating System :: OS Independent
